{
  "main": {
    "id": "881f0c77237027eb",
    "type": "split",
    "children": [
      {
        "id": "cb80bcd7713fdd1d",
        "type": "tabs",
        "children": [
          {
            "id": "3f6c655f7106e941",
            "type": "leaf",
            "state": {
              "type": "graph",
              "state": {}
            }
          }
        ]
      }
    ],
    "direction": "vertical"
  },
  "left": {
    "id": "861e67ccedb4750e",
    "type": "split",
    "children": [
      {
        "id": "c1d267af9aebc321",
        "type": "tabs",
        "children": [
          {
            "id": "3aebcde35dbaf390",
            "type": "leaf",
            "state": {
              "type": "file-explorer",
              "state": {
                "sortOrder": "alphabetical"
              }
            }
          },
          {
            "id": "1634f752e7f5df27",
            "type": "leaf",
            "state": {
              "type": "search",
              "state": {
                "query": "",
                "matchingCase": false,
                "explainSearch": false,
                "collapseAll": false,
                "extraContext": false,
                "sortOrder": "alphabetical"
              }
            }
          },
          {
            "id": "e141ada117115021",
            "type": "leaf",
            "state": {
              "type": "bookmarks",
              "state": {}
            }
          }
        ]
      }
    ],
    "direction": "horizontal",
    "width": 438.5
  },
  "right": {
    "id": "eed4b88d8ac2bae2",
    "type": "split",
    "children": [
      {
        "id": "2ff0ea48106213ed",
        "type": "tabs",
        "children": [
          {
            "id": "dd475a40208af1f7",
            "type": "leaf",
            "state": {
              "type": "backlink",
              "state": {
                "collapseAll": false,
                "extraContext": false,
                "sortOrder": "alphabetical",
                "showSearch": false,
                "searchQuery": "",
                "backlinkCollapsed": false,
                "unlinkedCollapsed": true
              }
            }
          },
          {
            "id": "2608c25de53716b6",
            "type": "leaf",
            "state": {
              "type": "outgoing-link",
              "state": {
                "linksCollapsed": false,
                "unlinkedCollapsed": true
              }
            }
          },
          {
            "id": "c7e260052d974100",
            "type": "leaf",
            "state": {
              "type": "tag",
              "state": {
                "sortOrder": "frequency",
                "useHierarchy": true
              }
            }
          },
          {
            "id": "2f859deabaf6a209",
            "type": "leaf",
            "state": {
              "type": "outline",
              "state": {}
            }
          }
        ]
      }
    ],
    "direction": "horizontal",
    "width": 300,
    "collapsed": true
  },
  "left-ribbon": {
    "hiddenItems": {
      "graph:Abrir vista gráfica": false,
      "command-palette:Abrir paleta de comandos": false
    }
  },
  "active": "3f6c655f7106e941",
  "lastOpenFiles": [
    "adjuntos/545.E2_recibiendo_1.png",
    "adjuntos/545.E2_install_9.png",
    "adjuntos/545.E2_install_8.png",
    "adjuntos/545.E2_install_7.png",
    "adjuntos/545.E2_install_6.png",
    "adjuntos/545.E2_install_5.png",
    "adjuntos/545.E2_install_4.png",
    "adjuntos/545.E2_install_3.png",
    "adjuntos/545.E2_install_2.png",
    "adjuntos/545.E2_install_1.png",
    "adjuntos/545.E2_enviando_4.png",
    "E2.Sistemas_Descentralizados/E2.U7.Modelos_de_negocio_con_un_nodo_LN_(BTC_PAY)/adjuntos",
    "E2.Sistemas_Descentralizados/E2.U6.Lightning_Network/542.E2.U6.3_Lightning_Network-Software.md",
    "E2.Sistemas_Descentralizados/E2.U5P.Aprende_a_conectarte_a_un_nodo_Bitcoin_Core_por_medio_de_la_interfaz_RPC_del_mismo/adjuntos",
    "E2.Sistemas_Descentralizados/E2.U5.Creando_tu_primer_nodo_de_Bitcoin_usando_Bitcoin_Core/adjuntos",
    "E2.Sistemas_Descentralizados/E2.U3.Minería_y_su_papel_en_Blockchain/adjuntos",
    "E2.Sistemas_Descentralizados/E2.U2.Maquinaria_para_Minería/adjuntos",
    "B7E3.Legislación_y_Ciberseguridad/adjuntos",
    "B7E3.Legislación_y_Ciberseguridad/439.B7E3.1_Normativas_legales_en_materia_de_Ciberseguridad.md",
    "B7E3.Legislación_y_Ciberseguridad/438.B7E3_Legislación-video.md",
    "B7E3.Legislación_y_Ciberseguridad",
    "-B7E3.Legislación_y_Ciberseguridad/adjuntos",
    "B1.Introducción_a_las_criptomonedas/B1.U7.Ethereum_2.0/68.B1.U7.3_Ethereum_2.0_-_La_evolución_de_Ethereum-Texto.md",
    "B4.Tecnologías_Descentralizadas/B4.U7.MetaMask/235.U7.1_Metamask.md",
    "E3.Estrategia/E3.U4.Análisis_de_Redes_Sociales/578.E3.U4.6_Google_Analytics.md",
    "E3.Estrategia/E3.U4.Análisis_de_Redes_Sociales/577.E3.U4.5_Herramientas_de_Analítica.md",
    "E3.Estrategia/E3.U4.Análisis_de_Redes_Sociales/576.E3.U4.4_SEO_y_SEM.md",
    "E3.Estrategia/E3.U4.Análisis_de_Redes_Sociales/575.E3.U4.3_CPM_y_CPC.md",
    "E3.Estrategia/E3.U4.Análisis_de_Redes_Sociales/574.E3_Análisis_de_Redes_Sociales-video.md",
    "E3.Estrategia/E3.U4.Análisis_de_Redes_Sociales/573.E3.U4.2_Las_Redes_Sociales_en_Cripto.md",
    "E3.Estrategia/E3.U4.Análisis_de_Redes_Sociales/572.E3_Las_Redes_Sociales_en_Cripto-video.md",
    "E3.Estrategia/E3.U4.Análisis_de_Redes_Sociales/571.E3.U4.1_Bulos,_Estafas_y_Fraudes.md",
    "E3.Estrategia/E3.U4.Análisis_de_Redes_Sociales/570.E3.U4.1_La_Cultura_Cripto.md",
    "E3.Estrategia/E3.U4.Análisis_de_Redes_Sociales/569.E3_La_Cultura_Cripto-video.md",
    "E3.Estrategia/E3.U3.Recursos_de_Gestión_de_Clientes/568.E3.U3.5_Herramientas_de_Implementación.md",
    "E3.Estrategia/E3.U3.Recursos_de_Gestión_de_Clientes/567.E3.U3.4_Maximización_de_retención.md",
    "E3.Estrategia/E3.U3.Recursos_de_Gestión_de_Clientes/566.E3.U3.3_Churn.md",
    "E3.Estrategia/E3.U3.Recursos_de_Gestión_de_Clientes/565.E3.U3.2_Funnel.md",
    "E3.Estrategia/E3.U3.Recursos_de_Gestión_de_Clientes/564.E3.U3.1_CAC_y_LTV.md",
    "E3.Estrategia/E3.U3.Recursos_de_Gestión_de_Clientes/563.E3_Recursos_de_Gestión_de_Clientes-video.md",
    "E3.Estrategia/E3.U1.Estudio_de_Mercado/553.E3.U1.4_Estudio_de_Mercado-Maximización_de_Valor.md",
    "E3.Estrategia/E3.U1.Estudio_de_Mercado/552.E3.U1.3_Estudio_de_Mercado-Branding.md",
    "E3.Estrategia/E3.U1.Estudio_de_Mercado/551.E3.U1.2_Estudio_de_Mercado-Segmentación_&_Targeting.md",
    "E3.Estrategia/E3.U1.Estudio_de_Mercado/550.E3.U1.1_Estudio_de_Mercado-Metodologías.md",
    "E3.Estrategia/E3.U4.Análisis_de_Redes_Sociales",
    "E3.Estrategia/E3.U3.Recursos_de_Gestión_de_Clientes"
  ]
}